__init__.py
scrapelite/__init__.py
scrapelite/_base_search.py
scrapelite/_github_search.py
scrapelite/_google_search.py
scrapelite-0.0.1.dist-info/LICENSE
scrapelite-0.0.1.dist-info/METADATA
scrapelite-0.0.1.dist-info/WHEEL
scrapelite-0.0.1.dist-info/top_level.txt
scrapelite-0.0.1.dist-info/RECORD
