Metadata-Version: 2.1
Name: scrapelite
Version: 0.0.1
Summary: A powerful web content fetcher and processor
Author-email: Your Name <your.email@example.com>
Project-URL: Homepage, https://github.com/yourusername/pyopengenai
Project-URL: Bug Tracker, https://github.com/yourusername/pyopengenai/issues
Classifier: Programming Language :: Python :: 3
Classifier: License :: OSI Approved :: MIT License
Classifier: Operating System :: OS Independent
Requires-Python: >=3.7
License-File: LICENSE
Requires-Dist: parselite
Requires-Dist: searchlite
